odoo/addons/mail_drop_target/README.rst
odoo/addons/mail_drop_target/__init__.py
odoo/addons/mail_drop_target/__manifest__.py
odoo/addons/mail_drop_target/controllers/__init__.py
odoo/addons/mail_drop_target/controllers/discuss.py
odoo/addons/mail_drop_target/i18n/it.po
odoo/addons/mail_drop_target/i18n/mail_drop_target.pot
odoo/addons/mail_drop_target/models/__init__.py
odoo/addons/mail_drop_target/models/ir_attachment.py
odoo/addons/mail_drop_target/models/mail_thread.py
odoo/addons/mail_drop_target/models/res_config_settings.py
odoo/addons/mail_drop_target/readme/CONFIGURATION.rst
odoo/addons/mail_drop_target/readme/CONTRIBUTORS.md
odoo/addons/mail_drop_target/readme/CREDITS.md
odoo/addons/mail_drop_target/readme/DESCRIPTION.md
odoo/addons/mail_drop_target/readme/ROADMAP.md
odoo/addons/mail_drop_target/readme/USAGE.md
odoo/addons/mail_drop_target/static/description/icon.png
odoo/addons/mail_drop_target/static/description/index.html
odoo/addons/mail_drop_target/static/src/js/file_uploader.esm.js
odoo/addons/mail_drop_target/tests/__init__.py
odoo/addons/mail_drop_target/tests/sample.eml
odoo/addons/mail_drop_target/tests/sample.msg
odoo/addons/mail_drop_target/tests/sample_include_attachment.msg
odoo/addons/mail_drop_target/tests/test_mail_drop_target.py
odoo/addons/mail_drop_target/views/res_config_settings_views.xml
odoo_addon_mail_drop_target-18.0.1.0.1.dist-info/METADATA
odoo_addon_mail_drop_target-18.0.1.0.1.dist-info/WHEEL
odoo_addon_mail_drop_target-18.0.1.0.1.dist-info/top_level.txt
odoo_addon_mail_drop_target-18.0.1.0.1.dist-info/RECORD
