Metadata-Version: 2.1
Name: odoo-addon-mail_drop_target
Version: 18.0.1.0.1
Requires-Python: >=3.10
Requires-Dist: extract_msg
Requires-Dist: odoo==18.0.*
Summary: Attach emails to Odoo by dragging them from your desktop
Home-page: https://github.com/OCA/mail
License: AGPL-3
Author: Therp BV,Odoo Community Association (OCA)
Author-email: support@odoo-community.org
Classifier: Programming Language :: Python
Classifier: Framework :: Odoo
Classifier: Framework :: Odoo :: 18.0
Classifier: License :: OSI Approved :: GNU Affero General Public License v3
